Metadata-Version: 2.1
Name: bert4torch
Version: 0.5.9.post2
Summary: an elegant bert4torch
Home-page: https://github.com/Tongjilibo/bert4torch
Author: Tongjilibo
Author-email: tongjilibo@163.com
License: MIT Licence
License-File: LICENSE
Requires-Dist: numpy
Requires-Dist: tqdm
Requires-Dist: torch>1.6
Requires-Dist: torch4keras==0.3.1
Requires-Dist: six
Provides-Extra: transformers
Requires-Dist: transformers; extra == "transformers"
Provides-Extra: accelerate
Requires-Dist: accelerate; extra == "accelerate"
Provides-Extra: deepspeed
Requires-Dist: deepspeed<=0.16.5,>=0.10.0; extra == "deepspeed"
Provides-Extra: trl
Requires-Dist: trl; extra == "trl"
Provides-Extra: peft
Requires-Dist: peft; extra == "peft"
